sgmlib/__init__.py
sgmlib-0.0.1.dist-info/METADATA
sgmlib-0.0.1.dist-info/WHEEL
sgmlib-0.0.1.dist-info/top_level.txt
sgmlib-0.0.1.dist-info/RECORD
